rlbot_smh/__init__.py
rlbot_smh/custom_map_util.py
rlbot_smh/get_missing_packages.py
rlbot_smh/match_handler.py
rlbot_smh/showroom_util.py
rlbot_smh/start_match_util.py
rlbot_smh/story_mode_util.py
rlbot_smh-1.0.13.dist-info/LICENSE.md
rlbot_smh-1.0.13.dist-info/METADATA
rlbot_smh-1.0.13.dist-info/WHEEL
rlbot_smh-1.0.13.dist-info/top_level.txt
rlbot_smh-1.0.13.dist-info/RECORD
