Metadata-Version: 2.1
Name: rlbot-smh
Version: 1.0.13
Summary: Start match helpers for RLBot
Author-email: VirxEC <virx@virxcase.dev>
Project-URL: Homepage, https://github.com/VirxEC/rlbot_smh
Project-URL: Bug Tracker, https://github.com/VirxEC/rlbot_smh/issues
Classifier: Programming Language :: Python :: 3
Classifier: License :: OSI Approved :: MIT License
Classifier: Operating System :: OS Independent
Requires-Python: >=3.6
License-File: LICENSE.md
